mcp_deployment-0.2.2.dist-info/licenses/LICENSE
mcpmanager/__init__.py
mcpmanager/exceptions.py
mcpmanager/py.typed
mcpmanager/api/__init__.py
mcpmanager/api/server.py
mcpmanager/auth/__init__.py
mcpmanager/auth/cedar.py
mcpmanager/auth/middleware.py
mcpmanager/certs/__init__.py
mcpmanager/certs/manager.py
mcpmanager/certs/store.py
mcpmanager/certs/validator.py
mcpmanager/cli/__init__.py
mcpmanager/cli/commands.py
mcpmanager/cli/main.py
mcpmanager/config/__init__.py
mcpmanager/config/manager.py
mcpmanager/container/__init__.py
mcpmanager/container/docker_client.py
mcpmanager/core/__init__.py
mcpmanager/core/discovery.py
mcpmanager/core/manager.py
mcpmanager/core/models.py
mcpmanager/core/protocol_schemes.py
mcpmanager/core/registry.py
mcpmanager/inspector/__init__.py
mcpmanager/inspector/debugger.py
mcpmanager/operator/__init__.py
mcpmanager/operator/controller.py
mcpmanager/operator/crd.py
mcpmanager/operator/operator.py
mcpmanager/permissions/__init__.py
mcpmanager/permissions/manager.py
mcpmanager/permissions/profiles.py
mcpmanager/runtime/__init__.py
mcpmanager/runtime/base.py
mcpmanager/runtime/docker_runtime.py
mcpmanager/runtime/kubernetes_runtime.py
mcpmanager/runtime/manager.py
mcpmanager/runtime/podman_runtime.py
mcpmanager/secrets/__init__.py
mcpmanager/secrets/manager.py
mcpmanager/telemetry/__init__.py
mcpmanager/telemetry/manager.py
mcpmanager/telemetry/metrics.py
mcpmanager/telemetry/middleware.py
mcpmanager/telemetry/tracing.py
mcpmanager/transport/__init__.py
mcpmanager/transport/base.py
mcpmanager/transport/factory.py
mcpmanager/transport/proxy.py
mcpmanager/transport/sse.py
mcpmanager/transport/stdio.py
mcpmanager/verification/__init__.py
mcpmanager/verification/attestation.py
mcpmanager/verification/policy.py
mcpmanager/verification/sigstore.py
mcpmanager/verification/verifier.py
mcp_deployment-0.2.2.dist-info/METADATA
mcp_deployment-0.2.2.dist-info/WHEEL
mcp_deployment-0.2.2.dist-info/entry_points.txt
mcp_deployment-0.2.2.dist-info/top_level.txt
mcp_deployment-0.2.2.dist-info/RECORD
