Metadata-Version: 2.4
Name: mcp-deployment
Version: 0.2.2
Summary: Secure MCP Server Management with Dynamic Discovery
Author: MCPManager Contributors
License-Expression: Apache-2.0
Keywords: mcp,model-context-protocol,containers,docker
Classifier: Development Status :: 4 - Beta
Classifier: Intended Audience :: Developers
Classifier: Operating System :: OS Independent
Classifier: Programming Language :: Python :: 3
Classifier: Programming Language :: Python :: 3.8
Classifier: Programming Language :: Python :: 3.9
Classifier: Programming Language :: Python :: 3.10
Classifier: Programming Language :: Python :: 3.11
Classifier: Programming Language :: Python :: 3.12
Classifier: Topic :: Software Development :: Libraries :: Python Modules
Classifier: Topic :: System :: Systems Administration
Classifier: Topic :: Internet :: WWW/HTTP :: HTTP Servers
Requires-Python: >=3.8
License-File: LICENSE
Requires-Dist: click>=8.0.0
Requires-Dist: docker>=6.0.0
Requires-Dist: pydantic>=2.0.0
Requires-Dist: requests>=2.25.0
Requires-Dist: fastapi>=0.100.0
Requires-Dist: uvicorn[standard]>=0.20.0
Requires-Dist: aiohttp>=3.8.0
Requires-Dist: cryptography>=3.0.0
Requires-Dist: keyring>=23.0.0
Requires-Dist: pyyaml>=6.0
Requires-Dist: jsonschema>=4.0.0
Requires-Dist: aiofiles>=23.0.0
Requires-Dist: httpx>=0.24.0
Requires-Dist: psutil>=5.8.0
Provides-Extra: kubernetes
Requires-Dist: kubernetes>=28.0.0; extra == "kubernetes"
Provides-Extra: telemetry
Requires-Dist: opentelemetry-api>=1.20.0; extra == "telemetry"
Requires-Dist: opentelemetry-sdk>=1.20.0; extra == "telemetry"
Requires-Dist: opentelemetry-exporter-otlp-proto-grpc>=1.20.0; extra == "telemetry"
Requires-Dist: opentelemetry-exporter-prometheus>=0.40b0; extra == "telemetry"
Requires-Dist: opentelemetry-exporter-jaeger-thrift>=1.20.0; extra == "telemetry"
Requires-Dist: opentelemetry-instrumentation-fastapi>=0.40b0; extra == "telemetry"
Requires-Dist: opentelemetry-instrumentation-httpx>=0.40b0; extra == "telemetry"
Requires-Dist: opentelemetry-instrumentation-requests>=0.40b0; extra == "telemetry"
Requires-Dist: opentelemetry-instrumentation-asyncio>=0.40b0; extra == "telemetry"
Requires-Dist: opentelemetry-instrumentation-logging>=0.40b0; extra == "telemetry"
Requires-Dist: opentelemetry-instrumentation-urllib3>=0.40b0; extra == "telemetry"
Provides-Extra: dev
Requires-Dist: pytest>=7.0.0; extra == "dev"
Requires-Dist: pytest-asyncio>=0.21.0; extra == "dev"
Requires-Dist: pytest-cov>=4.0.0; extra == "dev"
Requires-Dist: pytest-mock>=3.10.0; extra == "dev"
Requires-Dist: black>=23.0.0; extra == "dev"
Requires-Dist: isort>=5.0.0; extra == "dev"
Requires-Dist: flake8>=5.0.0; extra == "dev"
Requires-Dist: mypy>=1.0.0; extra == "dev"
Requires-Dist: pre-commit>=3.0.0; extra == "dev"
Requires-Dist: safety>=2.0.0; extra == "dev"
Requires-Dist: bandit>=1.7.0; extra == "dev"
Provides-Extra: auth
Requires-Dist: authlib>=1.2.0; extra == "auth"
Dynamic: license-file
